cooler_data_processor
