Metadata-Version: 2.1
Name: cooler-data-processor
Version: 0.2.2
Summary: A Cooler Data Processor
Home-page: UNKNOWN
Author: Charmi Patel
License: UNKNOWN
Platform: UNKNOWN
